{
  "id": "eco-l06",
  "code": "ECO",
  "course": "Managerial Economics",
  "no": 6,
  "title": "Market Structures",
  "simple_html": "<p>A <b>market structure</b> describes the competitive environment a firm operates in: how many rivals it faces, how similar their products are, and how easy it is for new firms to enter. Structure shapes a firm's <i>pricing power</i> — how much control it has over the price it charges.</p><p>Economists sort markets into four classic types along a spectrum from most to least competitive:</p><ul><li><b>Perfect competition</b> — many tiny firms selling identical products (e.g., wheat). No single firm can influence price; each is a <i>price taker</i>.</li><li><b>Monopolistic competition</b> — many firms selling similar-but-differentiated products (e.g., restaurants, salons). Each has a little pricing power through branding.</li><li><b>Oligopoly</b> — a few large firms that dominate (e.g., airlines, mobile carriers). Each watches and reacts to the others.</li><li><b>Monopoly</b> — one firm is the entire market (e.g., a regulated utility). It is a <i>price maker</i>, limited only by demand.</li></ul><p>Why it matters: the same cost and demand numbers produce very different prices, profits, and output depending on structure. A monopolist restricts output and charges more; perfectly competitive firms earn only normal profit in the long run because new entrants compete it away.</p><h4>Key takeaways</h4><ul><li>Three features define structure: <b>number of firms</b>, <b>product differentiation</b>, and <b>barriers to entry</b>.</li><li>More competition means less pricing power and lower long-run profit.</li><li><b>Barriers to entry</b> (patents, scale, brand, control of inputs) are what let firms keep profits over time.</li><li>The four types are a spectrum, not rigid boxes — most real industries sit somewhere in between.</li></ul>",
  "intermediate_html": "<p>Market structure analysis predicts how a firm will price, how much it will produce, and how profitable it can be over time. The structure is defined by three dimensions: the <b>number and size distribution of firms</b>, the degree of <b>product differentiation</b>, and the height of <b>barriers to entry and exit</b>. From these flow the firm's demand curve and therefore its pricing power.</p><h4>The four structures compared</h4><table><tr><th>Feature</th><th>Perfect Comp.</th><th>Monop. Comp.</th><th>Oligopoly</th><th>Monopoly</th></tr><tr><td>Firms</td><td>Very many</td><td>Many</td><td>Few</td><td>One</td></tr><tr><td>Product</td><td>Identical</td><td>Differentiated</td><td>Identical or differentiated</td><td>Unique</td></tr><tr><td>Entry barriers</td><td>None</td><td>Low</td><td>High</td><td>Very high</td></tr><tr><td>Pricing power</td><td>None (price taker)</td><td>Some</td><td>Substantial, interdependent</td><td>High (price maker)</td></tr><tr><td>Long-run profit</td><td>Normal only</td><td>Normal only</td><td>Can be positive</td><td>Positive</td></tr></table><h4>The common engine: MR = MC</h4><p>Every profit-maximizing firm, regardless of structure, produces where <code>MR = MC</code> (marginal revenue equals marginal cost). What differs is the shape of the demand curve the firm faces — and therefore its marginal revenue. The perfectly competitive firm faces a flat (perfectly elastic) demand at the market price, so <code>P = MR = MC</code>. Every other structure faces a downward-sloping demand curve, so <code>MR &lt; P</code>, and the firm sets <code>P &gt; MC</code> — the gap is its market power.</p><h4>Worked example</h4><p>A monopolist faces demand <code>P = 100 − Q</code> with constant <code>MC = 20</code>. Total revenue is <code>TR = 100Q − Q²</code>, so <code>MR = 100 − 2Q</code>. Setting <code>MR = MC</code>: <code>100 − 2Q = 20</code> gives <code>Q = 40</code>, and price <code>P = 100 − 40 = 60</code>. Now compare a perfectly competitive industry with the same cost: it would produce where <code>P = MC</code>, i.e., <code>100 − Q = 20</code>, so <code>Q = 80</code> at <code>P = 20</code>. The monopolist produces <b>half</b> the output at <b>three times</b> the price — the classic welfare cost of market power.</p><h4>How to apply it</h4><ul><li><b>Diagnose the structure first.</b> Count effective competitors, judge how substitutable the products are, and identify entry barriers before predicting behavior.</li><li><b>Map structure to strategy.</b> In monopolistic competition, invest in differentiation and brand; in oligopoly, anticipate rivals' reactions (this is where game theory enters — see Lesson 8).</li><li><b>Use concentration measures.</b> The <b>Herfindahl-Hirschman Index (HHI)</b> — the sum of squared market shares — quantifies concentration; antitrust authorities flag mergers that push HHI above ~2,500.</li><li><b>Remember the time horizon.</b> Short-run profits are possible everywhere; only barriers to entry let them persist into the long run.</li></ul><p>In short, structure is the lens that turns generic cost-and-demand data into concrete predictions about price, quantity, and profit — and into a strategy for sustaining advantage.</p>",
  "full_html": "<p>Market structure is the organizing framework of industrial economics: it classifies the competitive environment so that a manager can predict pricing, output, profitability, and the durability of advantage. The modern taxonomy descends from Edward Chamberlin and Joan Robinson's simultaneous 1933 reformulations of competition theory, and was systematized into the influential <i>Structure–Conduct–Performance (SCP) paradigm</i> by Joe Bain (Bain, 1956): the <b>structure</b> of a market (number of firms, differentiation, entry barriers) shapes firm <b>conduct</b> (pricing, advertising, R&amp;D), which in turn determines <b>performance</b> (profitability, efficiency, innovation).</p><h4>The defining dimensions</h4><p>Three structural variables determine which model applies:</p><ul><li><b>Number and size distribution of sellers</b> — from atomistic (perfect competition) to a single seller (monopoly).</li><li><b>Product differentiation</b> — whether goods are homogeneous (commodities) or differentiated (real or perceived).</li><li><b>Conditions of entry and exit</b> — the height of <b>barriers to entry</b>: economies of scale, patents and licenses, control of scarce inputs, network effects, brand capital, and sunk costs. Bain identified entry barriers as the central determinant of long-run profitability.</li></ul><h4>The four canonical structures</h4><p><b>Perfect competition.</b> Many small firms, homogeneous product, free entry, perfect information. Each firm is a price taker facing perfectly elastic demand, so <code>P = MR = MC</code>. In the long run, free entry drives economic profit to zero (firms earn only normal profit) and forces production at minimum average cost — the benchmark for allocative and productive efficiency.</p><p><b>Monopoly.</b> A single seller of a product with no close substitutes, protected by high entry barriers. The monopolist faces the entire downward-sloping market demand, so <code>MR &lt; P</code>. It maximizes profit at <code>MR = MC</code>, then prices off the demand curve at <code>P &gt; MC</code>. The result is restricted output, a price above marginal cost, supernormal profit, and a <b>deadweight loss</b> relative to the competitive ideal. The degree of power is captured by the <b>Lerner Index</b>, <code>L = (P − MC) / P</code>, which equals <code>−1/ε</code> for a monopolist facing elasticity <code>ε</code> (Lerner, 1934).</p><p><b>Monopolistic competition.</b> Chamberlin's contribution (Chamberlin, 1933): many firms, low entry barriers, but <i>differentiated</i> products. Each firm faces a downward-sloping but highly elastic demand and behaves like a small monopolist in the short run, earning profit at <code>MR = MC</code> with <code>P &gt; MC</code>. Low barriers then invite entry, which erodes each firm's demand until profit is competed away and the demand curve is tangent to average cost (zero economic profit) — but at an output below minimum AC. This <b>excess capacity</b> and the markup of price over marginal cost are the welfare costs of variety; the offsetting benefit is product diversity itself.</p><p><b>Oligopoly.</b> A few firms whose decisions are <b>mutually interdependent</b> — the defining and analytically hardest case, because each firm's best move depends on what rivals do. There is no single oligopoly model; instead a family of them: the <b>Cournot</b> model (firms choose quantities simultaneously; Cournot, 1838), the <b>Bertrand</b> model (firms choose prices, driving price to marginal cost with homogeneous goods), the <b>Stackelberg</b> model (a leader moves first and captures a first-mover advantage), and the <b>kinked demand curve</b> (Sweezy, 1939), which rationalizes price rigidity by assuming rivals match price cuts but not increases. Oligopoly is where market structure and <i>game theory</i> merge (see Lesson 8: Game Theory &amp; Strategic Interaction), since equilibrium is a Nash equilibrium of the firms' strategic choices.</p><h4>Worked example: monopoly vs. competition</h4><p>Suppose industry demand is <code>P = 120 − 2Q</code> and marginal cost is constant at <code>MC = 20</code> (no fixed cost). A perfectly competitive industry produces where <code>P = MC</code>: <code>120 − 2Q = 20</code>, so <code>Q = 50</code> at <code>P = 20</code> with zero economic profit. A monopolist with the same demand has <code>TR = 120Q − 2Q²</code>, hence <code>MR = 120 − 4Q</code>; setting <code>MR = MC</code> gives <code>120 − 4Q = 20</code>, so <code>Q = 25</code> and <code>P = 120 − 50 = 70</code>. Monopoly profit is <code>(70 − 20) × 25 = 1,250</code>. The deadweight loss is the triangle between the demand and MC curves over the lost output (25 to 50 units): <code>½ × (70 − 20) × (50 − 25) = 625</code>. This single calculation captures the textbook critique of market power: less output, higher price, transfer of surplus from consumers to the firm, and pure efficiency loss.</p><h4>Measuring structure empirically</h4><p>Managers and regulators quantify concentration with the <b>n-firm concentration ratio</b> (combined share of the top n firms) and, more rigorously, the <b>Herfindahl-Hirschman Index (HHI)</b> — the sum of squared percentage market shares, ranging from near 0 (atomistic) to 10,000 (monopoly). U.S. merger guidelines treat HHI above 2,500 as highly concentrated. These measures operationalize the structure dimension of SCP.</p><h4>Nuances and debates</h4><ul><li><b>Contestability.</b> Baumol, Panzar and Willig (1982) argued that what disciplines firms is not the <i>number</i> of incumbents but the <i>threat</i> of entry. A <b>perfectly contestable market</b> — free entry and costless exit (no sunk costs) — can force even a single incumbent to price competitively. This decouples performance from raw concentration.</li><li><b>SCP causality runs both ways.</b> The Chicago school (notably Demsetz, 1973) countered Bain by arguing that high concentration and high profits may both result from superior efficiency, not from anticompetitive conduct — the <i>efficiency hypothesis</i>. Conduct can also shape structure (predatory pricing, strategic entry deterrence), so the arrows are not one-directional.</li><li><b>Porter's bridge to strategy.</b> Porter's Five Forces (Porter, 1980) repurposed industrial-organization structure for the firm: structure determines industry attractiveness, and the firm's task is to position itself against the forces rather than take structure as fixed.</li></ul><h4>Common mistakes</h4><ul><li><b>Confusing few firms with monopoly.</b> Oligopoly behavior (interdependence) is qualitatively different from monopoly; applying monopoly's simple <code>MR = MC</code> ignores strategic reactions.</li><li><b>Assuming concentration equals market power.</b> Contestability and import competition can make a concentrated market behave competitively.</li><li><b>Forgetting the long run.</b> Short-run supernormal profit is possible in every structure; only entry barriers preserve it. Always state the time horizon.</li><li><b>Treating the four types as exhaustive boxes.</b> Real industries are hybrids; the models are reference points, not a complete partition of reality.</li></ul><p>Mastery means using structure as a diagnostic: identify the three dimensions, select the matching model, predict price and output via <code>MR = MC</code> on the relevant demand curve, quantify concentration and power (HHI, Lerner), and then layer on contestability and strategic conduct. This connects directly to Cost Theory (Lesson 5), which supplies the cost curves, and to Pricing Practices (Lesson 7) and Game Theory (Lesson 8), which extend conduct analysis.</p>",
  "concepts": [
    {"label": "Market Structures", "slug": "eco-market-structures"},
    {"label": "Monopoly", "slug": "eco-monopoly"},
    {"label": "Monopolistic Competition", "slug": "eco-monopolistic-competition"},
    {"label": "MR = MC Output", "slug": "eco-mr-mc-output"},
    {"label": "Lerner Index", "slug": "eco-lerner-index"},
    {"label": "Deadweight Loss", "slug": "eco-deadweight-loss"},
    {"label": "Oligopoly / Cournot", "slug": "eco-oligopoly-cournot"},
    {"label": "Profit Calculation", "slug": "eco-profit-calculation"}
  ]
}
